MicroBitTools.py
MicroBitTools-2.1.2.dist-info/LICENSE.txt
MicroBitTools-2.1.2.dist-info/METADATA
MicroBitTools-2.1.2.dist-info/WHEEL
MicroBitTools-2.1.2.dist-info/top_level.txt
MicroBitTools-2.1.2.dist-info/RECORD
