Metadata-Version: 2.1
Name: MicroBitTools
Version: 2.1.2
Summary: Library used for helping developing for the BBC microbit easier.
Home-page: https://github.com/BigCowKing/MicroBitTools
Author: Simon Lindgren
Author-email: babbilant@outlook.com
License: UNKNOWN
Platform: UNKNOWN
Classifier: Programming Language :: Python :: 3.7
Classifier: License :: OSI Approved :: GNU Affero General Public License v3
Classifier: Operating System :: Microsoft :: Windows :: Windows 10
Requires-Dist: requests
Requires-Dist: microfs
Requires-Dist: uflash
Requires-Dist: pyserial
